LICENCE
flake8_junit.py
pyproject.toml
flake8_junit-0.1.1.dist-info/entry_points.txt
flake8_junit-0.1.1.dist-info/WHEEL
flake8_junit-0.1.1.dist-info/METADATA
flake8_junit-0.1.1.dist-info/RECORD
