Metadata-Version: 2.1
Name: flake8-junit
Version: 0.1.1
Summary: JUnit assert statement checker plugin for flake8
Home-page: https://github.com/coin-tracker/flake8-junit
License: MIT
Keywords: flake8,plugin,linting,junit,code quality
Author: Pablo Marti Gamboa
Author-email: pablo@cointracker.io
Requires-Python: >=3.7
Classifier: Development Status :: 3 - Alpha
Classifier: Environment :: Console
Classifier: Framework :: Flake8
Classifier: Intended Audience :: Developers
Classifier: License :: OSI Approved :: MIT License
Classifier: Operating System :: OS Independent
Classifier: Programming Language :: Python
Classifier: Programming Language :: Python :: 3
Classifier: Programming Language :: Python :: 3.10
Classifier: Programming Language :: Python :: 3.7
Classifier: Programming Language :: Python :: 3.8
Classifier: Programming Language :: Python :: 3.9
Classifier: Topic :: Software Development :: Libraries :: Python Modules
Classifier: Topic :: Software Development :: Quality Assurance
Requires-Dist: flake8 (>=3.0)
Requires-Dist: pycodestyle
Project-URL: Repository, https://github.com/coin-tracker/flake8-junit
